fraier/__init__.py
fraier/fungsi_berat.py
fraier-0.1.0.dist-info/LICENSE
fraier-0.1.0.dist-info/METADATA
fraier-0.1.0.dist-info/WHEEL
fraier-0.1.0.dist-info/top_level.txt
fraier-0.1.0.dist-info/RECORD
