Metadata-Version: 2.1
Name: fraier
Version: 0.1.0
Summary: Deskripsi singkat paket
Author: akmal
Author-email: akmalrbc6@gmail.com
Classifier: Programming Language :: Python :: 3
Classifier: License :: OSI Approved :: MIT License
Classifier: Operating System :: OS Independent
Requires-Python: >=3.6
License-File: LICENSE
